maktab_dl/__init__.py
maktab_dl/cli.py
maktab_dl/handler.py
maktab_dl/logging.py
maktab_dl/schemas.py
maktab_dl/utils.py
maktab_dl-0.8.0.dist-info/licenses/LICENSE
maktab_dl-0.8.0.dist-info/METADATA
maktab_dl-0.8.0.dist-info/WHEEL
maktab_dl-0.8.0.dist-info/entry_points.txt
maktab_dl-0.8.0.dist-info/top_level.txt
maktab_dl-0.8.0.dist-info/RECORD
